pytorch_world-0.2.0.dist-info/licenses/LICENSE
world_models/__init__.py
world_models/controller/__init__.py
world_models/controller/rollout_generator.py
world_models/controller/rssm_policy.py
world_models/envs/__init__.py
world_models/envs/ale_atari_env.py
world_models/envs/ale_atari_vector_env.py
world_models/envs/dmc.py
world_models/envs/mujoco_env.py
world_models/envs/unity_env.py
world_models/envs/wrappers.py
world_models/memory/__init__.py
world_models/memory/dreamer_memory.py
world_models/memory/planet_memory.py
world_models/models/__init__.py
world_models/models/dreamer.py
world_models/models/dreamer_rssm.py
world_models/models/jepa_agent.py
world_models/models/planet.py
world_models/models/rssm.py
world_models/models/vit.py
world_models/reward/__init__.py
world_models/reward/dreamer_v1_reward.py
world_models/reward/dreamer_v1_value.py
world_models/training/__init__.py
world_models/training/train_jepa.py
world_models/training/train_planet.py
world_models/training/train_rssm.py
world_models/utils/__init__.py
world_models/utils/dreamer_utils.py
world_models/utils/jepa_utils.py
world_models/utils/utils.py
world_models/vision/__init__.py
world_models/vision/dreamer_decoder.py
world_models/vision/dreamer_encoder.py
world_models/vision/planet_decoder.py
world_models/vision/planet_encoder.py
pytorch_world-0.2.0.dist-info/METADATA
pytorch_world-0.2.0.dist-info/WHEEL
pytorch_world-0.2.0.dist-info/top_level.txt
pytorch_world-0.2.0.dist-info/RECORD
