Metadata-Version: 2.4
Name: pytorch-world
Version: 0.2.0
Summary: A Pytorch Based library for training world models
Author: 
License-Expression: MIT
Keywords: world-models,pytorch
Classifier: Programming Language :: Python :: 3
Classifier: Operating System :: OS Independent
Requires-Python: >=3.13
License-File: LICENSE
Requires-Dist: ale-py>=0.11.2
Requires-Dist: gym>=0.26.2
Requires-Dist: gymnasium>=1.2.2
Requires-Dist: mlagents-envs>=0.28.0
Requires-Dist: moviepy>=2.2.1
Requires-Dist: opencv-python>=4.12.0.88
Requires-Dist: plotly>=6.5.0
Requires-Dist: pre-commit>=4.5.0
Requires-Dist: pygame>=2.6.1
Requires-Dist: tensorboard>=2.20.0
Requires-Dist: tensorboardx>=2.6.4
Requires-Dist: tqdm>=4.67.1
Dynamic: license-file
Dynamic: requires-python
